pyhub_git_commit_apply/__init__.py
pyhub_git_commit_apply/__main__.py
pyhub_git_commit_apply/main.py
pyhub_git_commit_apply-0.4.0.dist-info/LICENSE
pyhub_git_commit_apply-0.4.0.dist-info/METADATA
pyhub_git_commit_apply-0.4.0.dist-info/WHEEL
pyhub_git_commit_apply-0.4.0.dist-info/entry_points.txt
pyhub_git_commit_apply-0.4.0.dist-info/top_level.txt
pyhub_git_commit_apply-0.4.0.dist-info/RECORD
