Metadata-Version: 2.2
Name: pyhub_git_commit_apply
Version: 0.4.0
Summary: A tool to download and apply changes from a GitHub commit URL
Author-email: Chinseok Lee <me@pyhub.kr>
License:                                  Apache License
Keywords: git,commit,github,apply
Classifier: Programming Language :: Python :: 3
Classifier: License :: OSI Approved :: MIT License
Classifier: Operating System :: OS Independent
Requires-Python: >=3.7
License-File: LICENSE
Provides-Extra: build
Requires-Dist: setuptools; extra == "build"
Requires-Dist: wheel; extra == "build"
Requires-Dist: build; extra == "build"
Requires-Dist: twine; extra == "build"
